discord_variables_plugin/Variables.py
discord_variables_plugin/__init__.py
discord_variables_plugin-1.2.dist-info/METADATA
discord_variables_plugin-1.2.dist-info/WHEEL
discord_variables_plugin-1.2.dist-info/top_level.txt
discord_variables_plugin-1.2.dist-info/RECORD
