Metadata-Version: 2.1
Name: discord-variables-plugin
Version: 1.2
Summary: A plugin to help with saving variables for Discord bots
Home-page: https://github.com/catjacks38/discord_variables_plugin
Author: catjacks38
License: UNKNOWN
Platform: UNKNOWN
Classifier: Operating System :: OS Independent
Classifier: License :: OSI Approved :: MIT License
Classifier: Programming Language :: Python :: 3
Requires-Python: >=3.5.3
